{
  "$schema": "https://ui.shadcn.com/schema/registry-item.json",
  "name": "dropdown-menu",
  "title": "Dropdown Menu",
  "description": "",
  "files": [
    {
      "path": "registry/bases/editframe/ui/dropdown-menu/index.tsx",
      "content": "\"use client\";\n\nimport { useFramecnTheme } from \"@/lib/framecn-ui\";\nimport type { FramecnTheme } from \"@/lib/framecn-ui\";\nimport {\n  dropdownMenuKeyframes,\n  dropdownMenuAnimation,\n} from \"@/registry/bases/editframe/ui/dropdown-menu/use-dropdown-menu-transition\";\n\nexport type DropdownMenuState = \"open\" | \"closed\";\n\nexport interface DropdownMenuProps {\n  state?: DropdownMenuState;\n  from?: DropdownMenuState;\n  label?: string;\n  items?: string[];\n  theme?: Partial<FramecnTheme>;\n  className?: string;\n  duration?: string;\n}\n\nexport interface DropdownMenuStyle {\n  chevronRotation: number;\n  panelOpacity: number;\n  panelScale: number;\n  panelTranslateY: number;\n}\n\nexport const dropdownMenuStyle = (\n  state: DropdownMenuState\n): DropdownMenuStyle => {\n  switch (state) {\n    case \"open\": {\n      return {\n        chevronRotation: 180,\n        panelOpacity: 1,\n        panelScale: 1,\n        panelTranslateY: 0,\n      };\n    }\n    default: {\n      return {\n        chevronRotation: 0,\n        panelOpacity: 0,\n        panelScale: 0.96,\n        panelTranslateY: -4,\n      };\n    }\n  }\n};\n\nexport const DropdownMenu = ({\n  state = \"closed\",\n  from,\n  label = \"Options\",\n  items = [\"Profile\", \"Settings\", \"Sign out\"],\n  theme: themeOverride,\n  className,\n  duration = \"12frames\",\n}: DropdownMenuProps) => {\n  const theme = useFramecnTheme(themeOverride, \"light\");\n  const v = dropdownMenuStyle(state);\n\n  const hasAnimation = from && from !== state;\n  const fromStyle = hasAnimation ? dropdownMenuStyle(from) : v;\n  const anim = hasAnimation\n    ? dropdownMenuAnimation(from, state, duration, fromStyle, v)\n    : {\n        chevronTransform: \"none\",\n        panelOpacity: \"none\",\n        panelTransform: \"none\",\n      };\n\n  const isOpen = state === \"open\";\n\n  return (\n    <div\n      style={{\n        alignItems: \"center\",\n        background: \"transparent\",\n        display: \"flex\",\n        fontFamily:\n          \"var(--font-geist-sans), -apple-system, BlinkMacSystemFont, sans-serif\",\n        inset: 0,\n        justifyContent: \"center\",\n        position: \"absolute\",\n      }}\n    >\n      {hasAnimation && <style>{dropdownMenuKeyframes(fromStyle, v)}</style>}\n      <div className={className} style={{ position: \"relative\" }}>\n        <button\n          type=\"button\"\n          style={{\n            alignItems: \"center\",\n            background: theme.background,\n            border: `1px solid ${theme.border}`,\n            borderRadius: theme.radius,\n            color: theme.foreground,\n            cursor: \"pointer\",\n            display: \"inline-flex\",\n            fontSize: 14,\n            fontWeight: 500,\n            gap: 8,\n            height: 40,\n            justifyContent: \"center\",\n            letterSpacing: \"-0.01em\",\n            padding: \"0 16px\",\n          }}\n        >\n          <span>{label}</span>\n          <svg\n            width={14}\n            height={14}\n            viewBox=\"0 0 24 24\"\n            fill=\"none\"\n            style={{\n              animation: hasAnimation ? anim.chevronTransform : undefined,\n              transform: `rotate(${v.chevronRotation}deg)`,\n            }}\n          >\n            <path\n              d=\"M6 9l6 6 6-6\"\n              stroke={theme.mutedForeground}\n              strokeWidth=\"2\"\n              strokeLinecap=\"round\"\n              strokeLinejoin=\"round\"\n            />\n          </svg>\n        </button>\n        {isOpen && (\n          <div\n            style={{\n              animation: hasAnimation\n                ? `${anim.panelOpacity}, ${anim.panelTransform}`\n                : undefined,\n              background: theme.popover,\n              border: `1px solid ${theme.border}`,\n              borderRadius: theme.radius,\n              boxShadow:\n                \"0 10px 15px -3px rgba(0,0,0,0.1), 0 4px 6px -4px rgba(0,0,0,0.1)\",\n              display: \"flex\",\n              flexDirection: \"column\",\n              left: 0,\n              opacity: v.panelOpacity,\n              padding: 4,\n              position: \"absolute\",\n              top: 44,\n              transform: `translateY(${v.panelTranslateY}px) scale(${v.panelScale})`,\n              transformOrigin: \"top\",\n              width: 160,\n              zIndex: 50,\n            }}\n          >\n            {items.map((item) => (\n              <button\n                key={item}\n                type=\"button\"\n                style={{\n                  alignItems: \"center\",\n                  background: \"transparent\",\n                  border: \"none\",\n                  borderRadius: theme.radius,\n                  color: theme.foreground,\n                  cursor: \"pointer\",\n                  display: \"flex\",\n                  fontSize: 14,\n                  fontWeight: 400,\n                  height: 36,\n                  padding: \"0 8px\",\n                  textAlign: \"left\",\n                  width: \"100%\",\n                }}\n              >\n                {item}\n              </button>\n            ))}\n          </div>\n        )}\n      </div>\n    </div>\n  );\n};\n",
      "type": "registry:ui"
    }
  ],
  "type": "registry:ui"
}