{
  "$schema": "https://ui.shadcn.com/schema/registry-item.json",
  "name": "highlight",
  "title": "Highlight",
  "description": "Word-by-word captions with an accent-colored highlight background that sweeps in behind each spoken word.",
  "dependencies": [
    "@editframe/react"
  ],
  "files": [
    {
      "path": "registry/bases/editframe/caption-highlight/index.tsx",
      "content": "\"use client\";\n\nimport { Timegroup } from \"@editframe/react\";\nimport type { CSSProperties } from \"react\";\n\nexport interface CaptionWord {\n  text: string;\n  start: number;\n  end: number;\n}\n\nexport interface CaptionHighlightProps {\n  words?: CaptionWord[];\n  color?: string;\n  highlightColor?: string;\n  highlightEndColor?: string;\n  highlightShadow?: string;\n  fontSize?: number;\n  fontWeight?: number | string;\n  fontFamily?: string;\n  background?: string;\n  speed?: number;\n  fps?: number;\n  durationInFrames?: number;\n  width?: number;\n  height?: number;\n  className?: string;\n}\n\nconst DEFAULT_WORDS: CaptionWord[] = [\n  { end: 0.3, start: 0, text: \"Every\" },\n  { end: 0.55, start: 0.3, text: \"great\" },\n  { end: 0.85, start: 0.55, text: \"video\" },\n  { end: 1.1, start: 0.85, text: \"starts\" },\n  { end: 1.25, start: 1.1, text: \"with\" },\n  { end: 1.35, start: 1.25, text: \"a\" },\n  { end: 1.65, start: 1.35, text: \"single\" },\n  { end: 2, start: 1.65, text: \"frame.\" },\n  { end: 2.65, start: 2.1, text: \"HyperFrames\" },\n  { end: 2.85, start: 2.65, text: \"lets\" },\n  { end: 2.95, start: 2.85, text: \"you\" },\n  { end: 3.15, start: 2.95, text: \"write\" },\n  { end: 3.55, start: 3.15, text: \"HTML\" },\n  { end: 3.65, start: 3.55, text: \"and\" },\n  { end: 3.95, start: 3.65, text: \"render\" },\n  { end: 4.45, start: 3.95, text: \"professional\" },\n  { end: 4.8, start: 4.45, text: \"video.\" },\n  { end: 5.05, start: 4.9, text: \"No\" },\n  { end: 5.45, start: 5.05, text: \"timeline.\" },\n  { end: 5.65, start: 5.5, text: \"No\" },\n  { end: 5.85, start: 5.65, text: \"drag\" },\n  { end: 5.95, start: 5.85, text: \"and\" },\n  { end: 6.25, start: 5.95, text: \"drop.\" },\n  { end: 6.55, start: 6.35, text: \"Just\" },\n  { end: 6.8, start: 6.55, text: \"code\" },\n  { end: 6.95, start: 6.8, text: \"that\" },\n  { end: 7.3, start: 6.95, text: \"becomes\" },\n  { end: 7.7, start: 7.3, text: \"cinema.\" },\n];\n\nconst RAW_GROUPS: [number, number][] = [\n  [0, 3],\n  [4, 7],\n  [8, 8],\n  [9, 12],\n  [13, 15],\n  [16, 16],\n  [17, 19],\n  [20, 22],\n  [23, 24],\n  [25, 27],\n];\n\nexport const CaptionHighlight = ({\n  words = DEFAULT_WORDS,\n  color: _color = \"#ffffff\",\n  highlightColor = \"#ff1745\",\n  highlightEndColor = \"#df1238\",\n  highlightShadow = \"rgba(229, 20, 58, 0.32)\",\n  fontSize = 80,\n  fontWeight = 800,\n  fontFamily = \"'Montserrat', sans-serif\",\n  background = \"transparent\",\n  speed = 1,\n  fps = 30,\n  durationInFrames = 240,\n  width = 1920,\n  height = 1080,\n  className,\n}: CaptionHighlightProps) => {\n  const safeSpeed = Math.max(0.01, speed);\n  const durationMs = (durationInFrames / fps) * 1000;\n\n  const groups = RAW_GROUPS.map(([ws, we], gi) => {\n    const nextStart =\n      gi + 1 < RAW_GROUPS.length\n        ? words[RAW_GROUPS[gi + 1][0]].start\n        : durationInFrames / fps;\n    const gEnd = Math.min(words[we].end + 0.5, nextStart - 0.05);\n    return {\n      end: gEnd,\n      start: words[ws].start,\n      wordEnd: we,\n      wordStart: ws,\n    };\n  });\n\n  const containerStyle: CSSProperties = {\n    background,\n    height,\n    overflow: \"hidden\",\n    position: \"relative\",\n    width,\n  };\n\n  return (\n    <Timegroup\n      className={className}\n      duration={`${durationMs}ms`}\n      mode=\"fixed\"\n      style={containerStyle}\n    >\n      <>\n        <style>{`\n          @keyframes ch-grp-show {\n            from { visibility: hidden; opacity: 0; }\n            to { visibility: visible; opacity: 1; }\n          }\n          @keyframes ch-grp-hide {\n            from { visibility: visible; opacity: 1; }\n            to { visibility: hidden; opacity: 0; }\n          }\n          @keyframes ch-grp-fade-in {\n            from { opacity: 0; }\n            to { opacity: 1; }\n          }\n          @keyframes ch-grp-fade-out {\n            from { opacity: 1; }\n            to { opacity: 0; }\n          }\n          @keyframes ch-bg-in {\n            from { opacity: 0; transform: scaleX(0); }\n            to { opacity: 1; transform: scaleX(1); }\n          }\n          @keyframes ch-bg-out {\n            from { opacity: 1; transform: scaleX(1); }\n            to { opacity: 0; transform: scaleX(1.02); }\n          }\n          @keyframes ch-bg-reset {\n            from { transform: scaleX(1.02); }\n            to { transform: scaleX(0); }\n          }\n          @keyframes ch-bright-in {\n            from { filter: brightness(1); }\n            to { filter: brightness(1.05); }\n          }\n          @keyframes ch-bright-out {\n            from { filter: brightness(1.05); }\n            to { filter: brightness(1); }\n          }\n        `}</style>\n        <div\n          style={\n            {\n              \"--ch-hl-color\": highlightColor,\n              \"--ch-hl-end-color\": highlightEndColor,\n              \"--ch-hl-shadow\": highlightShadow,\n              bottom: 140,\n              left: 0,\n              position: \"absolute\",\n              right: 0,\n            } as CSSProperties\n          }\n        >\n          {groups.map((g, gi) => {\n            const groupWords = words.slice(g.wordStart, g.wordEnd + 1);\n            const groupStartMs = (g.start * 1000) / safeSpeed;\n            const groupEndMs = (g.end * 1000) / safeSpeed;\n\n            return (\n              <div\n                key={gi}\n                style={{\n                  alignItems: \"flex-end\",\n                  animation: [\n                    `ch-grp-show 1ms linear ${groupStartMs}ms both`,\n                    `ch-grp-fade-in 120ms ease-out ${groupStartMs}ms both`,\n                    `ch-grp-fade-out 100ms ease-in ${groupEndMs - 100}ms forwards`,\n                    `ch-grp-hide 1ms linear ${groupEndMs}ms forwards`,\n                  ].join(\", \"),\n                  bottom: 140,\n                  display: \"flex\",\n                  flexWrap: \"wrap\",\n                  gap: \"8px\",\n                  justifyContent: \"center\",\n                  left: 0,\n                  padding: \"0 100px\",\n                  position: \"absolute\",\n                  right: 0,\n                  visibility: \"hidden\",\n                  width: \"100%\",\n                }}\n              >\n                {groupWords.map((word, i) => {\n                  const wi = g.wordStart + i;\n                  const wordStartMs = (word.start * 1000) / safeSpeed;\n                  const wordEndMs = (word.end * 1000) / safeSpeed;\n                  const bgInDuration = 150;\n                  const bgOutDuration = 100;\n                  const bgResetDelayMs = wordEndMs + 100;\n                  const brightInDuration = 80;\n                  const brightOutDuration = 160;\n                  const brightOutDelayMs = wordStartMs + 80;\n\n                  return (\n                    <span\n                      key={wi}\n                      style={{\n                        animation: [\n                          `ch-bright-in ${brightInDuration}ms ease-out ${wordStartMs}ms both`,\n                          `ch-bright-out ${brightOutDuration}ms ease-out ${brightOutDelayMs}ms forwards`,\n                        ].join(\", \"),\n                        display: \"inline-block\",\n                        fontFamily,\n                        fontSize,\n                        fontWeight,\n                        letterSpacing: \"0.02em\",\n                        lineHeight: 1,\n                        padding: \"6px 12px 8px\",\n                        position: \"relative\",\n                        textShadow: \"0 6px 18px rgba(0, 0, 0, 0.45)\",\n                        textTransform: \"uppercase\",\n                        willChange: \"filter\",\n                      }}\n                    >\n                      <span\n                        style={{\n                          animation: [\n                            `ch-bg-in ${bgInDuration}ms ease-out ${wordStartMs}ms both`,\n                            `ch-bg-out ${bgOutDuration}ms ease-in ${wordEndMs}ms forwards`,\n                            `ch-bg-reset 1ms linear ${bgResetDelayMs}ms forwards`,\n                          ].join(\", \"),\n                          background: `linear-gradient(135deg, var(--ch-hl-color) 0%, var(--ch-hl-end-color) 100%)`,\n                          borderRadius: 10,\n                          boxShadow: `0 12px 30px var(--ch-hl-shadow)`,\n                          inset: 0,\n                          opacity: 0,\n                          position: \"absolute\",\n                          transformOrigin: \"0% 50%\",\n                          willChange: \"transform, opacity\",\n                          zIndex: -1,\n                        }}\n                      />\n                      <span style={{ position: \"relative\", zIndex: 1 }}>\n                        {word.text.toUpperCase()}\n                      </span>\n                    </span>\n                  );\n                })}\n              </div>\n            );\n          })}\n        </div>\n      </>\n    </Timegroup>\n  );\n};\n",
      "type": "registry:component",
      "target": "components/framecn/highlight.tsx"
    }
  ],
  "type": "registry:component"
}